pyethapp/__init__.py
pyethapp/accounts.py
pyethapp/app.py
pyethapp/codernitydb_service.py
pyethapp/config.py
pyethapp/console_service.py
pyethapp/db_service.py
pyethapp/ephemdb_service.py
pyethapp/eth_protocol.py
pyethapp/eth_service.py
pyethapp/ipc_rpc.py
pyethapp/jsonrpc.py
pyethapp/leveldb_service.py
pyethapp/lmdb_service.py
pyethapp/monkeypatches.py
pyethapp/pow_service.py
pyethapp/profiles.py
pyethapp/rpc_client.py
pyethapp/sentry.py
pyethapp/synchronizer.py
pyethapp/utils.py
pyethapp/genesisdata/genesis_frontier.json
pyethapp/genesisdata/genesis_morden.json
pyethapp/genesisdata/genesis_olympic.json
pyethapp-1.5.0.dist-info/DESCRIPTION.rst
pyethapp-1.5.0.dist-info/METADATA
pyethapp-1.5.0.dist-info/RECORD
pyethapp-1.5.0.dist-info/WHEEL
pyethapp-1.5.0.dist-info/entry_points.txt
pyethapp-1.5.0.dist-info/metadata.json
pyethapp-1.5.0.dist-info/top_level.txt
