Metadata-Version: 2.0
Name: pyethapp
Version: 1.5.0
Summary: Python Ethereum Client
Home-page: https://github.com/ethereum/pyethapp
Author: HeikoHeiko
Author-email: heiko@ethdev.com
License: MIT
Keywords: pyethapp
Platform: UNKNOWN
Classifier: Development Status :: 2 - Pre-Alpha
Classifier: Intended Audience :: Developers
Classifier: License :: OSI Approved :: MIT License
Classifier: Natural Language :: English
Classifier: Programming Language :: Python :: 2
Classifier: Programming Language :: Python :: 2.7
Requires-Dist: CodernityDB
Requires-Dist: click
Requires-Dist: decorator
Requires-Dist: devp2p (>=0.8.0)
Requires-Dist: ethereum (>=1.5.1)
Requires-Dist: gevent (==1.1.0)
Requires-Dist: gipc (==0.4.0)
Requires-Dist: ipython (>=3.0.0,<5.0.0)
Requires-Dist: leveldb
Requires-Dist: lmdb
Requires-Dist: pbkdf2
Requires-Dist: pexpect
Requires-Dist: pyyaml
Requires-Dist: requests
Requires-Dist: rlp (>=0.4.4)
Requires-Dist: scrypt
Requires-Dist: statistics
Requires-Dist: werkzeug
Requires-Dist: wheel
